[{"name":"nsAMRT3tg","marks":23},{"name":"goO","marks":86},{"name":"6wA7j","marks":11},{"name":"5LIkYO","marks":43},{"name":"ZQ","marks":75},{"name":"LM9sFvE9B","marks":73},{"name":"X2","marks":95},{"name":"DY","marks":30},{"name":"wQnz8qPD","marks":38},{"name":"CEm","marks":58},{"name":"RJg1wrcKPY","marks":47},{"name":"8tgxY","marks":87},{"name":"nRFI","marks":22},{"name":"1aP6UN","marks":25},{"name":"nV5","marks":82},{"name":"RhfTSnS","marks":22},{"name":"zH","marks":24},{"name":"umDX6","marks":77},{"name":"90eQmDwG","marks":18},{"name":"8pi","marks":89},{"name":"D","marks":21},{"name":"M","marks":81},{"name":"q8dHXJH49","marks":23},{"name":"GAmLplcmM","marks":38},{"name":"DjTbJH0n","marks":93},{"name":"6xpbVA","marks":14},{"name":"Cc36","marks":95},{"name":"0B","marks":90},{"name":"kk3ECxH6","marks":77},{"name":"F","marks":77},{"name":"h","marks":98},{"name":"qqM","marks":43},{"name":"XVsjGR","marks":25},{"name":"dI7ho","marks":87},{"name":"kEvgyCpbL","marks":86},{"name":"zBSFjl","marks":25},{"name":"P","marks":99},{"name":"4dROXTkev6","marks":74},{"name":"qsxI3smy","marks":96},{"name":"1JF80n5","marks":92},{"name":"g","marks":22},{"name":"UFdQ","marks":28},{"name":"fGjdVvxW","marks":72},{"name":"wM3","marks":9},{"name":"U","marks":13},{"name":"kkbOK","marks":61},{"name":"u","marks":64},{"name":"4Lf","marks":7},{"name":"g5","marks":86},{"name":"mqQz","marks":66},{"name":"q","marks":61},{"name":"LHROgAn","marks":98},{"name":"36dzj","marks":23},{"name":"4wL9nk","marks":68},{"name":"UVg","marks":59},{"name":"4l","marks":85},{"name":"r1Bp","marks":25},{"name":"ondvcz","marks":70},{"name":"71blZrEmDS","marks":91},{"name":"FD7EKJNSKd","marks":48},{"name":"3qK","marks":73},{"name":"1KcfM","marks":79},{"name":"kzNq","marks":39},{"name":"rhv8HD4","marks":82},{"name":"vS0CUIO","marks":86},{"name":"mA","marks":39},{"name":"ld4J5","marks":43},{"name":"CjFB","marks":57},{"name":"4RyHU","marks":59},{"name":"nHxBnBTYo","marks":82},{"name":"jC6wSO19","marks":39},{"name":"S","marks":0},{"name":"Gaw","marks":60},{"name":"mlj","marks":13},{"name":"swtiUa0az1","marks":59},{"name":"cZT3v0a","marks":28},{"name":"oZg0cwM","marks":54},{"name":"SjYWG3guE7","marks":8},{"name":"CW","marks":39},{"name":"lOxA","marks":72},{"name":"xiPr","marks":81},{"name":"AtA7ucC","marks":42},{"name":"X","marks":75},{"name":"xeZlQ1FkW","marks":65},{"name":"tqXu6B","marks":11},{"name":"GuPD","marks":76},{"name":"dH","marks":86},{"name":"kxOZXZDs3","marks":37},{"name":"ArP17","marks":39},{"name":"guOiLiLcO6","marks":10},{"name":"aI","marks":53},{"name":"aG","marks":55},{"name":"uJHxmjD","marks":97},{"name":"7JtAa87","marks":6},{"name":"YgnsXzJY","marks":18},{"name":"Ugu07i","marks":51},{"name":"AsA9E","marks":36},{"name":"AirKa","marks":60},{"name":"HLr2dSi","marks":97},{"name":"paSl9N4","marks":72}]